sylenium/__init__.py
sylenium/_version.py
sylenium/constants.py
sylenium/sylenium.py
sylenium/configuration/__init__.py
sylenium/configuration/configuration.py
sylenium/core/__init__.py
sylenium/core/elements/locators.py
sylenium/core/pages/pageobjects.py
sylenium/core/sessions/session.py
sylenium/core/webdriver/driver_factories.py
sylenium/exceptions/__init__.py
sylenium/exceptions/exceptions.py
sylenium/helpers/_filesystem_helper.py
sylenium/helpers/_imports_helper.py
sylenium/helpers/_object_validator.py
sylenium/helpers/_os_environ_helper.py
sylenium/mixins/__init__.py
sylenium/mixins/simple_eq_mixin.py
sylenium/mixins/simple_repr_mixin.py
sylenium-1.0.1.dist-info/LICENSE
sylenium-1.0.1.dist-info/METADATA
sylenium-1.0.1.dist-info/WHEEL
sylenium-1.0.1.dist-info/top_level.txt
sylenium-1.0.1.dist-info/RECORD
